<?xml version="1.0" encoding="utf-8" ?>
<!--Created:cb85b80c-f585-40ff-8bfc-12ff4d0e34a9-->
<App xmlns="http://schemas.microsoft.com/sharepoint/2012/app/manifest"
     Name="SiteProvisioningWorkflow"
     ProductID="{16fd770a-4508-488e-b248-fcc8d5cbccfa}"
     Version="1.0.0.0"
     SharePointMinVersion="15.0.0.0"
>
  <Properties>
    <Title>Provisioning.Cloud.Workflow</Title>
    <StartPage>~remoteAppUrl/Pages/Default.aspx?{StandardTokens}</StartPage>
    <InstalledEventEndpoint>~remoteAppUrl/Services/AppEventReceiver.svc</InstalledEventEndpoint>
  </Properties>

  <AppPrincipal>
    <RemoteWebApplication ClientId="*" />
  </AppPrincipal>
  <AppPermissionRequests AllowAppOnlyPolicy="true">
    <AppPermissionRequest Scope="http://sharepoint/content/tenant" Right="FullControl" />
  </AppPermissionRequests>
</App>
